mojo/factories/mojointeroplandscapingfactories.py
mojo/factories/mojointeroptestplusfactories.py
mojo/interop/clients/clientroles.py
mojo/interop/clients/clientsourcepackager.py
mojo/interop/clients/constants.py
mojo/interop/clients/linux/__init__.py
mojo/interop/clients/linux/ext/commandsext.py
mojo/interop/clients/linux/ext/configureext.py
mojo/interop/clients/linux/linuxclient.py
mojo/interop/clients/linux/linuxclientcoordinator.py
mojo/interop/clients/linux/linuxclientcoordinatorcoupling.py
mojo/interop/clients/osx/__init__.py
mojo/interop/clients/osx/osxclient.py
mojo/interop/clients/osx/osxclientcoordinator.py
mojo/interop/clients/osx/osxclientcoordinatorcoupling.py
mojo/interop/clients/windows/__init__.py
mojo/interop/clients/windows/windowsclient.py
mojo/interop/clients/windows/windowsclientcoordinator.py
mojo/interop/clients/windows/windowsclientcoordinatorcoupling.py
mojo/interop/clusters/constants.py
mojo/interop/clusters/raspberrypi/__init__.py
mojo/interop/clusters/raspberrypi/picluster.py
mojo/interop/clusters/raspberrypi/pinode.py
mojo/interop/clusters/raspberrypi/pinodecoordinator.py
mojo/interop/clusters/raspberrypi/pinodecoordinatorcoupling.py
mojo/interop/protocols/dns/__init__.py
mojo/interop/protocols/dns/dnsaddress.py
mojo/interop/protocols/dns/dnsapi.py
mojo/interop/protocols/dns/dnsconst.py
mojo/interop/protocols/dns/dnshostinfo.py
mojo/interop/protocols/dns/dnsinboundmessage.py
mojo/interop/protocols/dns/dnsoutboundmessage.py
mojo/interop/protocols/dns/dnspointer.py
mojo/interop/protocols/dns/dnsquestion.py
mojo/interop/protocols/dns/dnsquestionresults.py
mojo/interop/protocols/dns/dnsrecord.py
mojo/interop/protocols/dns/dnsserver.py
mojo/interop/protocols/dns/dnsservice.py
mojo/interop/protocols/dns/dnstext.py
mojo/interop/protocols/dns/dnsutil.py
mojo/interop/protocols/dns/dnsvalidation.py
mojo/interop/protocols/dns/exceptions.py
mojo/interop/protocols/dns/mdnsagent.py
mojo/interop/protocols/dns/mdnsservicecatalog.py
mojo_interop-2.0.9.dist-info/LICENSE.txt
mojo_interop-2.0.9.dist-info/METADATA
mojo_interop-2.0.9.dist-info/WHEEL
mojo_interop-2.0.9.dist-info/RECORD
